<?xml version="1.0" encoding="UTF-8"?><database>
    <element attributes="update_synch=true" audit="true" extends="dl_matcher" label="demo Caller Lookup" max_length="40" name="x_501390_applicati_demo_caller_lookup" sizeclass="9" type="collection">
        <element choice="1" label="Impact" max_length="40" name="impact" type="choice">
            <choice>
                <element inactive_on_update="false" label="1 - High" value="1 - High"/>
                <element inactive_on_update="false" label="2 - Medium" value="2 - Medium"/>
                <element inactive_on_update="false" label="3 - Low" value="3 - Low"/>
            </choice>
        </element>
        <element choice="1" label="Priority" max_length="40" name="priority" type="choice">
            <choice>
                <element inactive_on_update="false" label="1 - Critical" value="1 - Critical"/>
                <element inactive_on_update="false" label="2 - High" value="2 - High"/>
                <element inactive_on_update="false" label="3 - Moderate" value="3 - Moderate"/>
                <element inactive_on_update="false" label="4 - Low" value="4 - Low"/>
            </choice>
        </element>
        <element choice="1" label="Urgency" max_length="40" name="urgency" type="choice">
            <choice>
                <element inactive_on_update="false" label="1 - High" value="1 - High"/>
                <element inactive_on_update="false" label="2 - Medium" value="2 - Medium"/>
                <element inactive_on_update="false" label="3 - Low" value="3 - Low"/>
            </choice>
        </element>
    </element>
</database>
